.coveragerc
.eslintrc
.mailmap
.testr.conf
AUTHORS
CONTRIBUTING.rst
ChangeLog
HACKING.rst
INSTALL.rst
LICENSE
MANIFEST.in
README.rst
babel.cfg
bindep.txt
manage.py
package.json
requirements.txt
run_tests.sh
setup.cfg
setup.py
test-requirements.txt
tox.ini
deployment/README.md
deployment/deploy.sh
deployment/catalog-ci-jenkins/manifests/site.pp
deployment/catalog-ci-jenkins/modules/catalog_ci/files/config.xml
deployment/catalog-ci-jenkins/modules/catalog_ci/files/gerrit-trigger.xml
deployment/catalog-ci-jenkins/modules/catalog_ci/files/jobs/job.yaml
deployment/catalog-ci-jenkins/modules/catalog_ci/files/scripts/app-catalog.sh
deployment/catalog-ci-jenkins/modules/catalog_ci/files/scripts/generate_names.py
deployment/catalog-ci-jenkins/modules/catalog_ci/manifests/init.pp
deployment/catalog-ci-jenkins/modules/catalog_ci/templates/jenkins_jobs.ini.erb
doc/source/conf.py
doc/source/contributing.rst
doc/source/index.rst
doc/source/installation.rst
doc/source/readme.rst
doc/source/usage.rst
openstack_app_catalog.egg-info/PKG-INFO
openstack_app_catalog.egg-info/SOURCES.txt
openstack_app_catalog.egg-info/dependency_links.txt
openstack_app_catalog.egg-info/entry_points.txt
openstack_app_catalog.egg-info/not-zip-safe
openstack_app_catalog.egg-info/pbr.json
openstack_app_catalog.egg-info/requires.txt
openstack_app_catalog.egg-info/top_level.txt
openstack_catalog/__init__.py
openstack_catalog/auth.py
openstack_catalog/cli.py
openstack_catalog/settings.py
openstack_catalog/static_settings.py
openstack_catalog/urls.py
openstack_catalog/views.py
openstack_catalog/wsgi.py
openstack_catalog/wsgi_django.py
openstack_catalog/api/__init__.py
openstack_catalog/api/v1.py
openstack_catalog/api/v2.py
openstack_catalog/plugins/__init__.py
openstack_catalog/plugins/glare/__init__.py
openstack_catalog/plugins/glare/import_from_yaml.py
openstack_catalog/plugins/glare/middlewares.py
openstack_catalog/plugins/glare/requirements.txt
openstack_catalog/templates/_scripts.html
openstack_catalog/templates/index.html
openstack_catalog/tests/__init__.py
openstack_catalog/tests/test_openstack_catalog.py
openstack_catalog/web/testicons.html
openstack_catalog/web/static/assets.schema.yaml
openstack_catalog/web/static/assets.yaml
openstack_catalog/web/static/assets_dead.yaml
openstack_catalog/web/static/blank.json
